rcp_colors/__init__.py
rcp_colors/rcp.py
rcp_colors-0.113.dist-info/METADATA
rcp_colors-0.113.dist-info/WHEEL
rcp_colors-0.113.dist-info/entry_points.txt
rcp_colors-0.113.dist-info/top_level.txt
rcp_colors-0.113.dist-info/RECORD
